comebackpy/__init__.py
comebackpy/comebackpy.py
comebackpy-1.0.0.dist-info/METADATA
comebackpy-1.0.0.dist-info/WHEEL
comebackpy-1.0.0.dist-info/top_level.txt
comebackpy-1.0.0.dist-info/RECORD
