Metadata-Version: 2.4
Name: ComeBackPy
Version: 1.0.0
Summary: A Python SDK for interacting with the ComeBackPy API
Author: Hemil Patel
Requires-Python: >=3.7
Requires-Dist: requests
Dynamic: author
Dynamic: requires-dist
Dynamic: requires-python
Dynamic: summary
